lionherd_core/__init__.py
lionherd_core/errors.py
lionherd_core/protocols.py
lionherd_core/py.typed
lionherd_core/base/__init__.py
lionherd_core/base/_utils.py
lionherd_core/base/broadcaster.py
lionherd_core/base/element.py
lionherd_core/base/event.py
lionherd_core/base/eventbus.py
lionherd_core/base/flow.py
lionherd_core/base/graph.py
lionherd_core/base/node.py
lionherd_core/base/pile.py
lionherd_core/base/processor.py
lionherd_core/base/progression.py
lionherd_core/libs/__init__.py
lionherd_core/libs/concurrency/__init__.py
lionherd_core/libs/concurrency/_cancel.py
lionherd_core/libs/concurrency/_errors.py
lionherd_core/libs/concurrency/_patterns.py
lionherd_core/libs/concurrency/_primitives.py
lionherd_core/libs/concurrency/_priority_queue.py
lionherd_core/libs/concurrency/_resource_tracker.py
lionherd_core/libs/concurrency/_run_async.py
lionherd_core/libs/concurrency/_task.py
lionherd_core/libs/concurrency/_utils.py
lionherd_core/libs/schema_handlers/__init__.py
lionherd_core/libs/schema_handlers/_function_call_parser.py
lionherd_core/libs/schema_handlers/_minimal_yaml.py
lionherd_core/libs/schema_handlers/_schema_to_model.py
lionherd_core/libs/schema_handlers/_typescript.py
lionherd_core/libs/string_handlers/__init__.py
lionherd_core/libs/string_handlers/_extract_json.py
lionherd_core/libs/string_handlers/_fuzzy_json.py
lionherd_core/libs/string_handlers/_string_similarity.py
lionherd_core/libs/string_handlers/_to_num.py
lionherd_core/ln/__init__.py
lionherd_core/ln/_async_call.py
lionherd_core/ln/_fuzzy_match.py
lionherd_core/ln/_fuzzy_validate.py
lionherd_core/ln/_hash.py
lionherd_core/ln/_json_dump.py
lionherd_core/ln/_list_call.py
lionherd_core/ln/_to_dict.py
lionherd_core/ln/_to_list.py
lionherd_core/ln/_utils.py
lionherd_core/lndl/__init__.py
lionherd_core/lndl/ast.py
lionherd_core/lndl/errors.py
lionherd_core/lndl/fuzzy.py
lionherd_core/lndl/lexer.py
lionherd_core/lndl/parser.py
lionherd_core/lndl/prompt.py
lionherd_core/lndl/resolver.py
lionherd_core-1.0.0a6.dist-info/METADATA
lionherd_core-1.0.0a6.dist-info/WHEEL
lionherd_core-1.0.0a6.dist-info/licenses/LICENSE
lionherd_core-1.0.0a6.dist-info/RECORD
