Metadata-Version: 2.4
Name: lionherd-core
Version: 1.0.0a6
Summary: The kernel layer for production AI agents - protocol-based, type-safe, zero framework lock-in
Project-URL: Homepage, https://github.com/khive-ai/lionherd-core
Project-URL: Documentation, https://github.com/khive-ai/lionherd-core/blob/main/README.md
Project-URL: Repository, https://github.com/khive-ai/lionherd-core
Project-URL: Issues, https://github.com/khive-ai/lionherd-core/issues
Project-URL: Changelog, https://github.com/khive-ai/lionherd-core/blob/main/CHANGELOG.md
Author-email: HaiyangLi <quantocean.li@gmail.com>
License: Apache-2.0
License-File: LICENSE
Keywords: agents,ai,async,llm,multi-agent,orchestration,protocols,type-safety
Classifier: Development Status :: 3 - Alpha
Classifier: Intended Audience :: Developers
Classifier: License :: OSI Approved :: Apache Software License
Classifier: Programming Language :: Python :: 3
Classifier: Programming Language :: Python :: 3.11
Classifier: Programming Language :: Python :: 3.12
Classifier: Programming Language :: Python :: 3.13
Classifier: Topic :: Scientific/Engineering :: Artificial Intelligence
Classifier: Topic :: Software Development :: Libraries :: Python Modules
Classifier: Typing :: Typed
Requires-Python: >=3.11
Requires-Dist: anyio>=4.7.0
Requires-Dist: pydapter>=1.2.0
Provides-Extra: all
Requires-Dist: datamodel-code-generator>=0.25.0; extra == 'all'
Provides-Extra: schema-gen
Requires-Dist: datamodel-code-generator>=0.25.0; extra == 'schema-gen'
